<ROUGE-EVAL version="1.55">
    <EVAL ID="1">
        <MODEL-ROOT>F:\Programs\Eclipse\CE_relation\CEsummary\kg\model_section_html</MODEL-ROOT>
        <PEER-ROOT>F:\Programs\Eclipse\CE_relation\CEsummary\kg\system_section_mance_temp_html\f0029.txt\s5</PEER-ROOT>
        <INPUT-FORMAT TYPE="SEE">
        </INPUT-FORMAT>
        <PEERS>
            <P ID="01">f0029.txt.s5.html.01</P>
			<P ID="05">f0029.txt.s5.html.05</P>
			<P ID="06">f0029.txt.s5.html.06</P>
			<P ID="07">f0029.txt.s5.html.07</P>
			<P ID="08">f0029.txt.s5.html.08</P>
			<P ID="09">f0029.txt.s5.html.09</P>
			<P ID="51">f0029.txt.s5.html.51</P>
			<P ID="55">f0029.txt.s5.html.55</P>
			<P ID="56">f0029.txt.s5.html.56</P>
			<P ID="57">f0029.txt.s5.html.57</P>
			<P ID="58">f0029.txt.s5.html.58</P>
			<P ID="59">f0029.txt.s5.html.59</P>
			
        </PEERS>
        <MODELS>
            <M ID="A">f0029.txt.s5.A.html</M>
			<M ID="B">f0029.txt.s5.B.html</M>
        </MODELS>
    </EVAL>
</ROUGE-EVAL>